apexdevkit/__init__.py
apexdevkit/annotation/__init__.py
apexdevkit/annotation/deprecate.py
apexdevkit/date.py
apexdevkit/environment.py
apexdevkit/error.py
apexdevkit/fastapi/__init__.py
apexdevkit/fastapi/builder.py
apexdevkit/fastapi/dependable.py
apexdevkit/fastapi/docs.py
apexdevkit/fastapi/name.py
apexdevkit/fastapi/resource.py
apexdevkit/fastapi/response.py
apexdevkit/fastapi/router.py
apexdevkit/fastapi/schema.py
apexdevkit/fastapi/service.py
apexdevkit/fluent.py
apexdevkit/formatter.py
apexdevkit/http/__init__.py
apexdevkit/http/fake.py
apexdevkit/http/fluent.py
apexdevkit/http/httpx/__init__.py
apexdevkit/http/httpx/client.py
apexdevkit/http/httpx/hooks.py
apexdevkit/http/json.py
apexdevkit/http/url.py
apexdevkit/id.py
apexdevkit/key_fn.py
apexdevkit/py.typed
apexdevkit/query/__init__.py
apexdevkit/query/generator.py
apexdevkit/query/query.py
apexdevkit/repository/__init__.py
apexdevkit/repository/base.py
apexdevkit/repository/connector.py
apexdevkit/repository/database.py
apexdevkit/repository/decorator.py
apexdevkit/repository/in_memory.py
apexdevkit/repository/interface.py
apexdevkit/repository/mssql.py
apexdevkit/repository/repository.py
apexdevkit/repository/sql.py
apexdevkit/repository/sqlite.py
apexdevkit/server.py
apexdevkit/synchronization.py
apexdevkit/testing/__init__.py
apexdevkit/testing/database.py
apexdevkit/testing/fake.py
apexdevkit/testing/rest.py
apexdevkit/value.py
apexdevkit-1.24.3.dist-info/METADATA
apexdevkit-1.24.3.dist-info/WHEEL
apexdevkit-1.24.3.dist-info/licenses/LICENSE
apexdevkit-1.24.3.dist-info/RECORD
