Metadata-Version: 2.4
Name: apexdevkit
Version: 1.24.3
Summary: Apex Development Tools for python.
License-File: LICENSE
Author: Apex Dev
Author-email: dev@apex.ge
Requires-Python: >=3.11
Classifier: Programming Language :: Python :: 3
Classifier: Programming Language :: Python :: 3.11
Classifier: Programming Language :: Python :: 3.12
Classifier: Programming Language :: Python :: 3.13
Classifier: Programming Language :: Python :: 3.14
Requires-Dist: fastapi
Requires-Dist: httpx
Requires-Dist: pymssql (==2.3.2)
Requires-Dist: python-dotenv
Requires-Dist: sentry-sdk[fastapi]
Requires-Dist: uvicorn
